hcluster/distance.py
hcluster/__init__.py
hcluster/_distance_wrap.cpython-36m-aarch64-linux-gnu.so
hcluster/hierarchy.py
hcluster/_hierarchy.cpython-36m-aarch64-linux-gnu.so
dedupe_hcluster-0.3.9.dist-info/METADATA
dedupe_hcluster-0.3.9.dist-info/LICENSE.txt
dedupe_hcluster-0.3.9.dist-info/WHEEL
dedupe_hcluster-0.3.9.dist-info/RECORD
dedupe_hcluster-0.3.9.dist-info/top_level.txt
