Metadata-Version: 2.1
Name: dedupe-hcluster
Version: 0.3.9
Summary: Hierarchical Clustering Algorithms (Information Theory)
Home-page: https://github.com/datamade/hcluster
Maintainer: Forest Gregg
Maintainer-email: fgregg@datamade.us
License: SciPy License (BSD Style)
Keywords: dendrogram,linkage,cluster,agglomorative,hierarchical,hierarchy,ward,distance
Platform: UNKNOWN
Classifier: Topic :: Scientific/Engineering :: Information Analysis
Classifier: Topic :: Scientific/Engineering :: Artificial Intelligence
Classifier: Topic :: Scientific/Engineering :: Bio-Informatics
Classifier: Programming Language :: Python
Classifier: Operating System :: OS Independent
Classifier: License :: OSI Approved :: BSD License
Classifier: Intended Audience :: Science/Research
Classifier: Development Status :: 4 - Beta
License-File: LICENSE.txt
Requires-Dist: numpy (>=1.10.4) ; python_version < "3.6"
Requires-Dist: numpy (>=1.12.1) ; python_version == "3.6"
Requires-Dist: numpy (>=1.15.0) ; python_version == "3.7"
Requires-Dist: numpy (>=1.17.3) ; python_version == "3.8"
Requires-Dist: numpy ; python_version > "3.8"
